decryption/__init__.py
decryption/decrypt.py
Decryption-1.0.1.dist-info/METADATA
Decryption-1.0.1.dist-info/WHEEL
Decryption-1.0.1.dist-info/top_level.txt
Decryption-1.0.1.dist-info/RECORD
