Metadata-Version: 2.1
Name: Decryption
Version: 1.0.1
Summary: This library can decrypt the Encrypted data and give response
Author: Surya
Requires-Dist: pycryptodome
